mkdocs_google_translate/__init__.py
mkdocs_google_translate/plugin.py
mkdocs_google_translate-1.3.1.dist-info/licenses/LICENSE
mkdocs_google_translate-1.3.1.dist-info/METADATA
mkdocs_google_translate-1.3.1.dist-info/WHEEL
mkdocs_google_translate-1.3.1.dist-info/entry_points.txt
mkdocs_google_translate-1.3.1.dist-info/top_level.txt
mkdocs_google_translate-1.3.1.dist-info/RECORD
