Metadata-Version: 2.4
Name: mkdocs-google-translate
Version: 1.3.1
Summary: A plugin to add relative links to Google Translate queries
Author-email: Sondre Grønås <mail@sondregronas.com>
License: MIT
Project-URL: homepage, https://github.com/sondregronas/mkdocs-google-translate
Project-URL: documentation, https://github.com/sondregronas/mkdocs-google-translate
Project-URL: repository, https://github.com/sondregronas/mkdocs-google-translate
Project-URL: issues, https://github.com/sondregronas/mkdocs-google-translate/issues
Project-URL: funding, https://github.com/sponsors/sondregronas
Keywords: mkdocs,markdown,google,translate
Classifier: Development Status :: 5 - Production/Stable
Classifier: License :: OSI Approved :: MIT License
Classifier: Programming Language :: Python
Classifier: Programming Language :: Python :: 3
Classifier: Programming Language :: Python :: 3 :: Only
Classifier: Topic :: Documentation
Classifier: Topic :: Software Development :: Documentation
Requires-Python: >=3.8
License-File: LICENSE
Requires-Dist: mkdocs>=1
Provides-Extra: tests
Requires-Dist: pytest; extra == "tests"
Dynamic: license-file
